<?xml version="1.0" encoding="UTF-8"?>
<workspaceFilter version="1.0">
    <filter root="/apps/sling/servlet/errorhandler" mode="merge"/>
	<filter root="/apps/settings/wcm/designs/commons" mode="replace"/>
	<filter root="/apps/core/wcm/components/page/v2/page/cq:infoProviders" mode="update"/>
	<filter root="/apps/plas/components" mode="update"/>
    <filter root="/apps/plas/config" mode="replace"/>
	<filter root="/apps/plas/config.author" mode="replace"/>
	<filter root="/apps/plas/config.publish" mode="replace"/>
	<filter root="/apps/plas/config.dev.author" mode="replace"/>
	<filter root="/apps/plas/config.dev.publish" mode="replace"/>
	<filter root="/apps/plas/config.prod.author" mode="replace"/>
	<filter root="/apps/plas/config.prod.publish" mode="replace"/>
	<filter root="/apps/plas/config.qa.author" mode="replace"/>
	<filter root="/apps/plas/config.qa.publish" mode="replace"/>
	<filter root="/apps/plas/config.stage.author" mode="replace"/>
	<filter root="/apps/plas/config.stage.publish" mode="replace"/>
	<filter root="/apps/plas/install" mode="update"/>
	<filter root="/apps/plas/clientlibs" mode="update"/>
	<filter root="/apps/plas/i18n">
		<exclude pattern="/apps/plas/i18n(/.*)?"/>
	</filter>
	<filter root="/apps/plas/ac-config"/>
	<filter root="/apps/msm/plas" mode="update"/>
</workspaceFilter>
